vflexctl/__init__.py
vflexctl/cli.py
vflexctl/command/__init__.py
vflexctl/command/led.py
vflexctl/command/voltage.py
vflexctl/context.py
vflexctl/device_interface/__init__.py
vflexctl/device_interface/common_sequences.py
vflexctl/device_interface/vflex.py
vflexctl/exceptions.py
vflexctl/input_handler/voltage_convert.py
vflexctl/main.py
vflexctl/midi_transport/receivers.py
vflexctl/midi_transport/senders.py
vflexctl/protocol/__init__.py
vflexctl/protocol/coders/__init__.py
vflexctl/protocol/coders/led_state.py
vflexctl/protocol/coders/serial_number.py
vflexctl/protocol/coders/voltage.py
vflexctl/protocol/command_framing.py
vflexctl/protocol/logger.py
vflexctl/protocol/protocol.py
vflexctl/py.typed
vflexctl/types.py
vflexctl-0.2.0.dist-info/METADATA
vflexctl-0.2.0.dist-info/WHEEL
vflexctl-0.2.0.dist-info/entry_points.txt
vflexctl-0.2.0.dist-info/licenses/LICENSE
vflexctl-0.2.0.dist-info/RECORD
