Metadata-Version: 2.4
Name: vflexctl
Version: 0.2.0
Summary: Command line tool to set the output voltage for VFLEX devices
License: Apache 2.0
License-File: LICENSE
Author: hameedm
Author-email: hameedm@protonmail.com
Requires-Python: >=3.12,<4.0
Classifier: License :: Other/Proprietary License
Classifier: Programming Language :: Python :: 3
Classifier: Programming Language :: Python :: 3.12
Classifier: Programming Language :: Python :: 3.13
Classifier: Programming Language :: Python :: 3.14
Requires-Dist: colorama (>=0.4.6,<0.5.0)
Requires-Dist: mido (>=1.3.3,<2.0.0)
Requires-Dist: pydantic (>=2.12.5,<3.0.0)
Requires-Dist: pytest (>=9.0.1,<10.0.0)
Requires-Dist: python-rtmidi (>=1.5.8,<2.0.0)
Requires-Dist: rich (>=14.2.0,<15.0.0)
Requires-Dist: structlog (>=25.5.0,<26.0.0)
Requires-Dist: typer (>=0.20.0,<0.21.0)
